script_menu_widget/02-script_menu_widget.omero
script_menu_widget/__init__.py
script_menu_widget/apps.py
script_menu_widget/setup_integration.py
script_menu_widget/urls.py
script_menu_widget/views.py
script_menu_widget/static/scriptmenu/css/pretty_buttons.css
script_menu_widget/static/scriptmenu/css/scrip_cards_color.css
script_menu_widget/static/scriptmenu/css/style.css
script_menu_widget/static/scriptmenu/img/script-text-play.svg
script_menu_widget/static/scriptmenu/js/color_me.js
script_menu_widget/static/scriptmenu/js/main.js
script_menu_widget/static/scriptmenu/js/remove_ugly_buttons.js
script_menu_widget/static/scriptmenu/js/script_menu.js
script_menu_widget/static/scriptmenu/js/search_scripts.js
script_menu_widget/templates/scriptmenu/webclient_plugins/script_launch_head.html
script_menu_widget/templates/scriptmenu/webclient_plugins/script_menu_widget.html
omero_script_menu_widget-1.2.2.dist-info/LICENSE
omero_script_menu_widget-1.2.2.dist-info/METADATA
omero_script_menu_widget-1.2.2.dist-info/WHEEL
omero_script_menu_widget-1.2.2.dist-info/entry_points.txt
omero_script_menu_widget-1.2.2.dist-info/top_level.txt
omero_script_menu_widget-1.2.2.dist-info/RECORD
