Metadata-Version: 2.1
Name: omero-script-menu-widget
Version: 1.2.2
Summary: A Python plugin for OMERO.web
Home-page: https://github.com/Cellular-Imaging-Amsterdam-UMC/omero-script-menu-widget/tree/master
Author: The Open Microscopy Team
Author-email: rrosas@amsterdamumc.nl
License: AGPL-3.0
Download-URL: https://github.com/Cellular-Imaging-Amsterdam-UMC/omero-script-menu-widget/archive/refs/heads/master.zip
Keywords: OMERO.web,plugin
Platform: UNKNOWN
Classifier: Development Status :: 5 - Production/Stable
Classifier: Environment :: Web Environment
Classifier: Framework :: Django
Classifier: Intended Audience :: Developers
Classifier: Natural Language :: English
Classifier: Operating System :: OS Independent
Classifier: Programming Language :: JavaScript
Classifier: Programming Language :: Python :: 3
Classifier: Topic :: Internet :: WWW/HTTP
Classifier: Topic :: Internet :: WWW/HTTP :: Dynamic Content
Classifier: Topic :: Internet :: WWW/HTTP :: WSGI
Classifier: Topic :: Scientific/Engineering :: Visualization
Classifier: Topic :: Software Development :: Libraries :: Application Frameworks
Classifier: Topic :: Software Development :: Testing
Classifier: Topic :: Text Processing :: Markup :: HTML
Requires-Python: >=3
Requires-Dist: omero-web >=5.6.0
